{
    "$schema": "http://json-schema.org/draft-07/schema#",
    "definitions": {
        "entityData": {
            "title": "Entity Data",
            "description": "Schema for defining Minecraft entity data.",
            "type": "object",
            "properties": {
                "Air": {
                    "type": "string",
                    "default": 0,
                    "title": "Air"
                },
                "CustomName": {
                    "$ref": "text_component.json#/definitions/textComponent"
                },
                "CustomNameVisible": {
                    "type": "boolean",
                    "title": "CustomNameVisible"
                },
                "data": {
                    
                }
            }
        }
    }
}